[
	{
		"id": 1,
		"image": "/src/assets/Jallabiya/jallabiya_1.png",

		"name": "AZ Jalabiya 001",
		"price": 160000
	},
	{
		"id": 2,
		"image": "/src/assets/Jallabiya/jallabiya_2.png",
		"name": "AZ Jalabiya 002",
		"price": 40000
	},
	{
		"id": 3,
		"image": "/src/assets/Jallabiya/jallabiya_3.png",
		"name": "AZ Jalabiya 0003",
		"price": 40000
	},
	{
		"id": 4,
		"image": "/src/assets/Jallabiya/jallabiya_4.png",
		"name": "AZ Jalabiya 004",
		"price": 180000
	},
	{
		"id": 5,
		"image": "/src/assets/Jallabiya/jallabiya_5.png",
		"name": "AZ Jalabiya 0005",
		"price": 160000
	},
	{
		"id": 6,
		"image": "/src/assets/Jallabiya/jallabiya_6.png",
		"name": "AZ Jalabiya 006",
		"price": 40000
	},
	{
		"id": 7,
		"image": "/src/assets/Jallabiya/jallabiya_7.png",
		"name": "AZ Jalabiya 007",
		"price": 40000
	},
	{
		"id": 8,
		"image": "/src/assets/Jallabiya/jallabiya_8.png",
		"name": "AZ Jalabiya 008",
		"price": 180000
	},
	{
		"id": 9,
		"image": "/src/assets/Jallabiya/jallabiya_1.png",

		"name": "AZ Jalabiya 001",
		"price": 160000
	},
	{
		"id": 10,
		"image": "/src/assets/Jallabiya/jallabiya_2.png",
		"name": "AZ Jalabiya 002",
		"price": 40000
	},
	{
		"id": 11,
		"image": "/src/assets/Jallabiya/jallabiya_3.png",
		"name": "AZ Jalabiya 0003",
		"price": 40000
	},
	{
		"id": 12,
		"image": "/src/assets/Jallabiya/jallabiya_4.png",
		"name": "AZ Jalabiya 004",
		"price": 180000
	},
	{
		"id": 13,
		"image": "/src/assets/Jallabiya/jallabiya_5.png",
		"name": "AZ Jalabiya 0005",
		"price": 160000
	},
	{
		"id": 14,
		"image": "/src/assets/Jallabiya/jallabiya_6.png",
		"name": "AZ Jalabiya 006",
		"price": 40000
	},
	{
		"id": 15,
		"image": "/src/assets/Jallabiya/jallabiya_7.png",
		"name": "AZ Jalabiya 007",
		"price": 40000
	},
	{
		"id": 16,
		"image": "/src/assets/Jallabiya/jallabiya_8.png",
		"name": "AZ Jalabiya 008",
		"price": 180000
	}
]
